{"Event": {"EventId": 254, "Name": "Strikeforce - Playboy Mansion", "StartTime": "2007-09-29T04:00Z", "TimeZone": "GMT-07:00", "Status": "Over", "LiveEventId": 1225, "LiveFightId": 11610, "LiveRoundNumber": 1, "LiveRoundElapsedTime": "2:07", "Location": {"City": "Beverly Hills", "State": "California", "Country": "USA", "TriCode": "USA", "VenueId": 177, "Venue": "The Playboy Mansion"}}, "FightId": 2468, "FightOrder": 12, "Status": "Final", "OfficialStats": true, "CardSegment": null, "CardSegmentStartTime": null, "CardSegmentBroadcaster": null, "Fighters": [{"FighterId": 1235, "MMAId": null, "Name": {"FirstName": "Anthony", "LastName": "Figueroa", "NickName": null}, "Born": {"City": null, "State": null, "Country": null, "TriCode": null}, "FightingOutOf": {"City": null, "State": null, "Country": null, "TriCode": null}, "Record": {"Wins": 11, "Losses": 8, "Draws": 1, "NoContests": 0}, "DOB": null, "Age": null, "Stance": "Orthodox", "Weight": 135.0, "Height": 64.0, "Reach": null, "UFCLink": "http://www.ufc.com/athlete/Anthony-Figueroa", "WeightClasses": [], "Corner": "Red", "WeighIn": 133.0, "Outcome": {"OutcomeId": 1, "Outcome": "Win"}, "KOOfTheNight": false, "SubmissionOfTheNight": false, "PerformanceOfTheNight": false}, {"FighterId": 1256, "MMAId": null, "Name": {"FirstName": "Miguel", "LastName": "Linares", "NickName": null}, "Born": {"City": null, "State": null, "Country": null, "TriCode": null}, "FightingOutOf": {"City": null, "State": null, "Country": null, "TriCode": null}, "Record": {"Wins": 2, "Losses": 4, "Draws": 0, "NoContests": 0}, "DOB": null, "Age": null, "Stance": null, "Weight": 0.0, "Height": 0.0, "Reach": null, "UFCLink": "http://www.ufc.com/athlete/Miguel-Linares", "WeightClasses": [], "Corner": "Blue", "WeighIn": 135.0, "Outcome": {"OutcomeId": 2, "Outcome": "Loss"}, "KOOfTheNight": false, "SubmissionOfTheNight": false, "PerformanceOfTheNight": false}], "Result": {"Method": "KO/TKO", "EndingRound": 1, "EndingTime": "2:09", "EndingStrike": "Punches", "EndingTarget": "Head", "EndingPosition": "In Clinch", "EndingSubmission": null, "EndingNotes": null, "FightOfTheNight": false, "FightScores": [], "RoundScores": []}, "WeightClass": {"WeightClassId": 7, "CatchWeight": null, "Weight": "126-135", "Description": "Bantamweight", "Abbreviation": "BW"}, "Accolades": [], "Referee": {"RefereeId": 79, "FirstName": "Marcos", "LastName": "Rosales"}, "RuleSet": {"PossibleRounds": 3, "Description": "3 Rnd (3-3-3)"}, "FightStats": [{"FighterId": 1235, "Knockdowns": 1, "TotalStrikesAttempted": 32, "TotalStrikesLanded": 21, "TotalHeadStrikesAttempted": 20, "TotalHeadStrikesLanded": 11, "TotalBodyStrikesAttempted": 8, "TotalBodyStrikesLanded": 8, "TotalLegStrikesAttempted": 4, "TotalLegStrikesLanded": 2, "TotalClinchStrikesAttempted": 16, "TotalClinchStrikesLanded": 14, "TotalGroundStrikesAttempted": 4, "TotalGroundStrikesLanded": 3, "SigStrikesAttempted": 30, "SigStrikesLanded": 19, "SigStrikesAccuracy": 63.33, "SigHeadStrikesAttempted": 20, "SigHeadStrikesLanded": 11, "SigBodyStrikesAttempted": 6, "SigBodyStrikesLanded": 6, "SigLegStrikesAttempted": 4, "SigLegStrikesLanded": 2, "SigDistanceStrikesAttempted": 12, "SigDistanceStrikesLanded": 4, "SigClinchStrikesAttempted": 14, "SigClinchStrikesLanded": 12, "SigGroundStrikesAttempted": 4, "SigGroundStrikesLanded": 3, "SigDistanceHeadStrikesAttempted": 7, "SigDistanceHeadStrikesLanded": 1, "SigDistanceBodyStrikesAttempted": 1, "SigDistanceBodyStrikesLanded": 1, "SigDistanceLegStrikesAttempted": 4, "SigDistanceLegStrikesLanded": 2, "SigClinchHeadStrikesAttempted": 10, "SigClinchHeadStrikesLanded": 8, "SigClinchBodyStrikesAttempted": 4, "SigClinchBodyStrikesLanded": 4, "SigClinchLegStrikesAttempted": 0, "SigClinchLegStrikesLanded": 0, "SigGroundHeadStrikesAttempted": 3, "SigGroundHeadStrikesLanded": 2, "SigGroundBodyStrikesAttempted": 1, "SigGroundBodyStrikesLanded": 1, "SigGroundLegStrikesAttempted": 0, "SigGroundLegStrikesLanded": 0, "TakedownsAttempted": 0, "TakedownsLanded": 0, "TakedownsAccuracy": null, "Reversals": 0, "SubmissionsAttempted": 0, "NeutralTime": null, "StandingTime": null, "DistanceTime": null, "ClinchTime": null, "GroundTime": null, "ControlTime": null, "GroundControlTime": null, "MiscGroundControlTime": null, "GuardControlTime": null, "HalfGuardControlTime": null, "SideControlTime": null, "MountControlTime": null, "BackControlTime": null}, {"FighterId": 1256, "Knockdowns": 0, "TotalStrikesAttempted": 28, "TotalStrikesLanded": 14, "TotalHeadStrikesAttempted": 18, "TotalHeadStrikesLanded": 6, "TotalBodyStrikesAttempted": 1, "TotalBodyStrikesLanded": 1, "TotalLegStrikesAttempted": 9, "TotalLegStrikesLanded": 7, "TotalClinchStrikesAttempted": 3, "TotalClinchStrikesLanded": 3, "TotalGroundStrikesAttempted": 0, "TotalGroundStrikesLanded": 0, "SigStrikesAttempted": 28, "SigStrikesLanded": 14, "SigStrikesAccuracy": 50.0, "SigHeadStrikesAttempted": 18, "SigHeadStrikesLanded": 6, "SigBodyStrikesAttempted": 1, "SigBodyStrikesLanded": 1, "SigLegStrikesAttempted": 9, "SigLegStrikesLanded": 7, "SigDistanceStrikesAttempted": 25, "SigDistanceStrikesLanded": 11, "SigClinchStrikesAttempted": 3, "SigClinchStrikesLanded": 3, "SigGroundStrikesAttempted": 0, "SigGroundStrikesLanded": 0, "SigDistanceHeadStrikesAttempted": 16, "SigDistanceHeadStrikesLanded": 4, "SigDistanceBodyStrikesAttempted": 0, "SigDistanceBodyStrikesLanded": 0, "SigDistanceLegStrikesAttempted": 9, "SigDistanceLegStrikesLanded": 7, "SigClinchHeadStrikesAttempted": 2, "SigClinchHeadStrikesLanded": 2, "SigClinchBodyStrikesAttempted": 1, "SigClinchBodyStrikesLanded": 1, "SigClinchLegStrikesAttempted": 0, "SigClinchLegStrikesLanded": 0, "SigGroundHeadStrikesAttempted": 0, "SigGroundHeadStrikesLanded": 0, "SigGroundBodyStrikesAttempted": 0, "SigGroundBodyStrikesLanded": 0, "SigGroundLegStrikesAttempted": 0, "SigGroundLegStrikesLanded": 0, "TakedownsAttempted": 0, "TakedownsLanded": 0, "TakedownsAccuracy": null, "Reversals": 0, "SubmissionsAttempted": 0, "NeutralTime": null, "StandingTime": null, "DistanceTime": null, "ClinchTime": null, "GroundTime": null, "ControlTime": null, "GroundControlTime": null, "MiscGroundControlTime": null, "GuardControlTime": null, "HalfGuardControlTime": null, "SideControlTime": null, "MountControlTime": null, "BackControlTime": null}], "RoundStats": [{"FighterId": 1235, "Rounds": [{"RoundNumber": 1, "Knockdowns": 1, "TotalStrikesAttempted": 32, "TotalStrikesLanded": 21, "TotalHeadStrikesAttempted": 20, "TotalHeadStrikesLanded": 11, "TotalBodyStrikesAttempted": 8, "TotalBodyStrikesLanded": 8, "TotalLegStrikesAttempted": 4, "TotalLegStrikesLanded": 2, "TotalClinchStrikesAttempted": 16, "TotalClinchStrikesLanded": 14, "TotalGroundStrikesAttempted": 4, "TotalGroundStrikesLanded": 3, "SigStrikesAttempted": 30, "SigStrikesLanded": 19, "SigStrikesAccuracy": 63.33, "SigHeadStrikesAttempted": 20, "SigHeadStrikesLanded": 11, "SigBodyStrikesAttempted": 6, "SigBodyStrikesLanded": 6, "SigLegStrikesAttempted": 4, "SigLegStrikesLanded": 2, "SigDistanceStrikesAttempted": 12, "SigDistanceStrikesLanded": 4, "SigClinchStrikesAttempted": 14, "SigClinchStrikesLanded": 12, "SigGroundStrikesAttempted": 4, "SigGroundStrikesLanded": 3, "SigDistanceHeadStrikesAttempted": 7, "SigDistanceHeadStrikesLanded": 1, "SigDistanceBodyStrikesAttempted": 1, "SigDistanceBodyStrikesLanded": 1, "SigDistanceLegStrikesAttempted": 4, "SigDistanceLegStrikesLanded": 2, "SigClinchHeadStrikesAttempted": 10, "SigClinchHeadStrikesLanded": 8, "SigClinchBodyStrikesAttempted": 4, "SigClinchBodyStrikesLanded": 4, "SigClinchLegStrikesAttempted": 0, "SigClinchLegStrikesLanded": 0, "SigGroundHeadStrikesAttempted": 3, "SigGroundHeadStrikesLanded": 2, "SigGroundBodyStrikesAttempted": 1, "SigGroundBodyStrikesLanded": 1, "SigGroundLegStrikesAttempted": 0, "SigGroundLegStrikesLanded": 0, "TakedownsAttempted": 0, "TakedownsLanded": 0, "TakedownsAccuracy": null, "Reversals": 0, "SubmissionsAttempted": 0, "NeutralTime": null, "StandingTime": null, "DistanceTime": null, "ClinchTime": null, "GroundTime": null, "ControlTime": null, "GroundControlTime": null, "MiscGroundControlTime": null, "GuardControlTime": null, "HalfGuardControlTime": null, "SideControlTime": null, "MountControlTime": null, "BackControlTime": null}]}, {"FighterId": 1256, "Rounds": [{"RoundNumber": 1, "Knockdowns": 0, "TotalStrikesAttempted": 28, "TotalStrikesLanded": 14, "TotalHeadStrikesAttempted": 18, "TotalHeadStrikesLanded": 6, "TotalBodyStrikesAttempted": 1, "TotalBodyStrikesLanded": 1, "TotalLegStrikesAttempted": 9, "TotalLegStrikesLanded": 7, "TotalClinchStrikesAttempted": 3, "TotalClinchStrikesLanded": 3, "TotalGroundStrikesAttempted": 0, "TotalGroundStrikesLanded": 0, "SigStrikesAttempted": 28, "SigStrikesLanded": 14, "SigStrikesAccuracy": 50.0, "SigHeadStrikesAttempted": 18, "SigHeadStrikesLanded": 6, "SigBodyStrikesAttempted": 1, "SigBodyStrikesLanded": 1, "SigLegStrikesAttempted": 9, "SigLegStrikesLanded": 7, "SigDistanceStrikesAttempted": 25, "SigDistanceStrikesLanded": 11, "SigClinchStrikesAttempted": 3, "SigClinchStrikesLanded": 3, "SigGroundStrikesAttempted": 0, "SigGroundStrikesLanded": 0, "SigDistanceHeadStrikesAttempted": 16, "SigDistanceHeadStrikesLanded": 4, "SigDistanceBodyStrikesAttempted": 0, "SigDistanceBodyStrikesLanded": 0, "SigDistanceLegStrikesAttempted": 9, "SigDistanceLegStrikesLanded": 7, "SigClinchHeadStrikesAttempted": 2, "SigClinchHeadStrikesLanded": 2, "SigClinchBodyStrikesAttempted": 1, "SigClinchBodyStrikesLanded": 1, "SigClinchLegStrikesAttempted": 0, "SigClinchLegStrikesLanded": 0, "SigGroundHeadStrikesAttempted": 0, "SigGroundHeadStrikesLanded": 0, "SigGroundBodyStrikesAttempted": 0, "SigGroundBodyStrikesLanded": 0, "SigGroundLegStrikesAttempted": 0, "SigGroundLegStrikesLanded": 0, "TakedownsAttempted": 0, "TakedownsLanded": 0, "TakedownsAccuracy": null, "Reversals": 0, "SubmissionsAttempted": 0, "NeutralTime": null, "StandingTime": null, "DistanceTime": null, "ClinchTime": null, "GroundTime": null, "ControlTime": null, "GroundControlTime": null, "MiscGroundControlTime": null, "GuardControlTime": null, "HalfGuardControlTime": null, "SideControlTime": null, "MountControlTime": null, "BackControlTime": null}]}]}